finite_state_machines/FSM.py
finite_state_machines/MVWFSM.py
finite_state_machines/WFSM.py
finite_state_machines/__init__.py
finite_state_machines/combinatorial_fsm.py
finite_state_machines/algorithms/__init__.py
finite_state_machines/algorithms/fsm_for_words_avoiding.py
finite_state_machines-1.2.2.dist-info/LICENSE.txt
finite_state_machines-1.2.2.dist-info/METADATA
finite_state_machines-1.2.2.dist-info/WHEEL
finite_state_machines-1.2.2.dist-info/top_level.txt
finite_state_machines-1.2.2.dist-info/RECORD
