Metadata-Version: 2.1
Name: finite-state-machines
Version: 1.2.2
Summary: A library for manipulating finite state machines
Home-page: https://github.com/jaypantone/FiniteStateMachines
Author: Jay Pantone
Author-email: jay.pantone@gmail.com
License: UNKNOWN
Project-URL: Bug Tracker, https://github.com/jaypantone/FiniteStateMachines/issues
Platform: UNKNOWN
Classifier: Development Status :: 5 - Production/Stable
Classifier: Intended Audience :: Education
Classifier: Intended Audience :: Science/Research
Classifier: Programming Language :: Python :: 3
Classifier: License :: OSI Approved :: MIT License
Classifier: Operating System :: OS Independent
Classifier: Programming Language :: Python :: Implementation :: CPython
Classifier: Programming Language :: Python :: Implementation :: PyPy
Classifier: Topic :: Education
Classifier: Topic :: Scientific/Engineering :: Mathematics
Requires-Python: >=3.7
License-File: LICENSE.txt
